{"key":"C","title":"小星星","bpm":45,"beatFlag":"4:4","type":"CHORD","loop":"1@|@2@|@3@|@4@|@5","capo":0,"measures":[{"index":1,"beats":[{"index":1,"note":{"noteInfo":"1:0","effect":""},"length":1.0},{"index":2,"note":{"noteInfo":"1:0","effect":""},"length":1.0},{"index":3,"note":{"noteInfo":"1:7","effect":""},"length":1.0},{"index":4,"note":{"noteInfo":"1:7","effect":""},"length":1.0}]},{"index":2,"beats":[{"index":1,"note":{"noteInfo":"1:9","effect":""},"length":1.0},{"index":2,"note":{"noteInfo":"1:9","effect":""},"length":1.0},{"index":3,"note":{"noteInfo":"1:7","effect":""},"length":1.0},{"index":4,"length":1.0}]},{"index":3,"beats":[{"index":1,"note":{"noteInfo":"1:5","effect":""},"length":1.0},{"index":2,"note":{"noteInfo":"1:5","effect":""},"length":1.0},{"index":3,"note":{"noteInfo":"1:4","effect":""},"length":1.0},{"index":4,"note":{"noteInfo":"1:4","effect":""},"length":1.0}]},{"index":4,"beats":[{"index":1,"note":{"noteInfo":"1:2","effect":""},"length":1.0},{"index":2,"note":{"noteInfo":"1:2","effect":""},"length":1.0},{"index":3,"note":{"noteInfo":"1:0","effect":""},"length":1.0},{"index":4,"length":1.0}]},{"index":5,"beats":[{"index":1,"length":4.0}]}]}